processmanager/__init__.py
processmanager/exceptions.py
processmanager/globalvars.py
processmanager/helpers.py
processmanager/initialization.py
processmanager/mainprocessglobals.py
processmanager/notifications.py
processmanager/notificationtypes.py
processmanager/requestmonitor.py
processmanager/termination.py
processmanager/validation.py
processmanager/workerglobals.py
processmanager/workers.py
processmanager/workrequestclasses.py
processmanager/workrequests.py
processmanager-0.1.1.dist-info/COPYING
processmanager-0.1.1.dist-info/COPYING.LESSER
processmanager-0.1.1.dist-info/LICENSE
processmanager-0.1.1.dist-info/METADATA
processmanager-0.1.1.dist-info/WHEEL
processmanager-0.1.1.dist-info/top_level.txt
processmanager-0.1.1.dist-info/RECORD
