Metadata-Version: 2.1
Name: processmanager
Version: 0.1.1
Summary: A multiprocessing process manager for Python programs
Home-page: UNKNOWN
Author: Brandon M. Pace
Author-email: brandonmpace@gmail.com
License: GNU Lesser General Public License v3 or later
Project-URL: Code and Issues, https://github.com/brandonmpace/processmanager
Project-URL: Documentation, https://processmanager.readthedocs.io
Keywords: multiprocessing multicore process offload manager
Platform: any
Classifier: Development Status :: 4 - Beta
Classifier: License :: OSI Approved :: GNU Lesser General Public License v3 or later (LGPLv3+)
Classifier: Operating System :: OS Independent
Classifier: Programming Language :: Python :: 3
Requires-Python: >=3.6.5
Requires-Dist: freezehelper (>=2.0.0)
Requires-Dist: logcontrol (>=0.2.1)
